LICENCE
README.md
setup.py
signer_icpedu/__init__.py
signer_icpedu/signer.py
signer_icpedu.egg-info/PKG-INFO
signer_icpedu.egg-info/SOURCES.txt
signer_icpedu.egg-info/dependency_links.txt
signer_icpedu.egg-info/requires.txt
signer_icpedu.egg-info/top_level.txt