Metadata-Version: 2.1
Name: signer-icpedu
Version: 0.0.1
Summary: Package para assinaturas digitais
Author: Kemuel dos Santos Rocha
Author-email: kemuel.rocha@discente.univasf.edu.br
License: MIT License
Keywords: signer icpedu
License-File: LICENCE
